torch_cryoeraser/__init__.py
torch_cryoeraser/erase.py
torch_cryoeraser/sparse_local_mean.py
torch_cryoeraser/utils.py
torch_cryoeraser-0.1.0.dist-info/METADATA
torch_cryoeraser-0.1.0.dist-info/WHEEL
torch_cryoeraser-0.1.0.dist-info/licenses/LICENSE
torch_cryoeraser-0.1.0.dist-info/RECORD
