Metadata-Version: 2.4
Name: torch-cryoeraser
Version: 0.1.0
Summary: Erase masked regions from cryo-EM images
Project-URL: homepage, https://github.com/teamtomo/torch-cryoeraser
Project-URL: repository, https://github.com/teamtomo/torch-cryoeraser
Author-email: Alister Burt <alisterburt@gmail.com>
License: BSD-3-Clause
License-File: LICENSE
Classifier: Development Status :: 3 - Alpha
Classifier: License :: OSI Approved :: BSD License
Classifier: Programming Language :: Python :: 3
Classifier: Programming Language :: Python :: 3.9
Classifier: Programming Language :: Python :: 3.10
Classifier: Programming Language :: Python :: 3.11
Classifier: Programming Language :: Python :: 3.12
Classifier: Programming Language :: Python :: 3.13
Classifier: Typing :: Typed
Requires-Python: >=3.9
Requires-Dist: einops
Requires-Dist: numpy
Requires-Dist: scipy
Requires-Dist: torch
Provides-Extra: dev
Requires-Dist: ipython; extra == 'dev'
Requires-Dist: matplotlib; extra == 'dev'
Requires-Dist: mkdocs-jupyter; extra == 'dev'
Requires-Dist: mkdocs-material; extra == 'dev'
Requires-Dist: mkdocstrings[python]; extra == 'dev'
Requires-Dist: pdbpp; extra == 'dev'
Requires-Dist: pooch; extra == 'dev'
Requires-Dist: rich; extra == 'dev'
Requires-Dist: tifffile; extra == 'dev'
Provides-Extra: examples
Requires-Dist: matplotlib; extra == 'examples'
Requires-Dist: pooch; extra == 'examples'
Requires-Dist: tifffile; extra == 'examples'
Provides-Extra: test
Requires-Dist: pytest; extra == 'test'
Requires-Dist: pytest-cov; extra == 'test'
